{"index.md":"DrEYDuWg","前端知识库_0-html_index.md":"BLZKg1ZU","备忘录_index.md":"DIuOIr9l","前端知识库_4-vite_0-vite基础.md":"DuwCGfTZ","前端知识库_2-javascript_index.md":"DddIccwr","前端知识库_2-javascript_1-如何判断一个元素是否在可视区域中.md":"C0Z1JW2V","前端知识库_1-css_1-单文件组件中css的功能.md":"CIjKBgJ-","前端知识库_1-css_0-css基础.md":"kmSYnLf5","百宝箱_朋友圈表情包.md":"cfWNA8LT","前端知识库_3-vue_index.md":"C9yenWJe","前端知识库_3-vue_0-vue基础.md":"B4SIKoj3","备忘录_生日表.md":"B-12wzxN","前端知识库_0-html_0-html基础.md":"DJR5le8T","前端知识库_2-javascript_0-javascript基础.md":"FZs6Zrli","前端知识库_1-css_index.md":"CEzq8tqm","前端知识库_3-vue_2-elementplus组件测试.md":"npboYAiP","前端知识库_3-vue_1-vue组件的二次封装.md":"DO0VIxZF","百宝箱_index.md":"C5Wf5Hgc","前端知识库_4-vite_index.md":"DOQ_l88h","前端知识库_4-vite_2-vitepress-sidebar插件的使用.md":"DMjtzyOj","前端知识库_4-vite_1-vite常用基本配置.md":"L5L_DsGt"}
